sitemap_generate/__init__.py
sitemap_generate/defaults.py
sitemap_generate/generator.py
sitemap_generate/management/__init__.py
sitemap_generate/management/commands/__init__.py
sitemap_generate/management/commands/generate_sitemap.py
testproject/__init__.py
testproject/asgi.py
testproject/settings.py
testproject/urls.py
testproject/wsgi.py
testproject/testapp/__init__.py
testproject/testapp/apps.py
testproject/testapp/models.py
testproject/testapp/sitemaps.py
testproject/testapp/tests.py
testproject/testapp/urls.py
testproject/testapp/views.py
testproject/testapp/migrations/0001_initial.py
testproject/testapp/migrations/__init__.py
django_sitemap_generate-0.7.0.dist-info/LICENSE
django_sitemap_generate-0.7.0.dist-info/METADATA
django_sitemap_generate-0.7.0.dist-info/WHEEL
django_sitemap_generate-0.7.0.dist-info/top_level.txt
django_sitemap_generate-0.7.0.dist-info/RECORD
