Metadata-Version: 2.1
Name: django-sitemap-generate
Version: 0.7.0
Summary: Background sitemap generation for Django
Home-page: https://github.com/just-work/django-sitemap-generate
Author: Sergey Tikhonov
Author-email: zimbler@gmail.com
License: MIT
Classifier: Development Status :: 4 - Beta
Classifier: Environment :: Console
Classifier: Framework :: Django :: 3.2
Classifier: Framework :: Django :: 4.2
Classifier: Framework :: Django :: 5.0
Classifier: Operating System :: POSIX
Classifier: Programming Language :: Python :: 3.8
Classifier: Programming Language :: Python :: 3.9
Classifier: Programming Language :: Python :: 3.10
Classifier: Programming Language :: Python :: 3.11
Classifier: Programming Language :: Python :: 3.12
Classifier: Topic :: Internet :: WWW/HTTP :: Dynamic Content :: Content Management System
License-File: LICENSE
Requires-Dist: Django<5.1,>=3.2
